sqlalchemy_heavyai/__init__.py
sqlalchemy_heavyai/base.py
sqlalchemy_heavyai/heavyai.py
sqlalchemy_heavyai/provision.py
sqlalchemy_heavyai/requirements.py
sqlalchemy_heavyai/util.py
sqlalchemy_heavyai/version.py
sqlalchemy_heavyai-1.0.dist-info/entry_points.txt
sqlalchemy_heavyai-1.0.dist-info/LICENSE.md
sqlalchemy_heavyai-1.0.dist-info/WHEEL
sqlalchemy_heavyai-1.0.dist-info/METADATA
sqlalchemy_heavyai-1.0.dist-info/RECORD
