Metadata-Version: 2.1
Name: sqlalchemy-heavyai
Version: 1.0
Summary: HeavyAI SQLAlchemy Driver
Author-email: "Heavy.AI" <community@heavy.ai>
Requires-Python: >=3.7
Classifier: License :: OSI Approved :: MIT License
Classifier: Topic :: Database
Classifier: Topic :: Scientific/Engineering
Requires-Dist: sqlalchemy
Requires-Dist: heavyai
Requires-Dist: importlib_metadata
Requires-Dist: sqlalchemy-heavyai[test] ; extra == "dev"
Requires-Dist: sqlalchemy-heavyai[doc] ; extra == "dev"
Requires-Dist: pre-commit ; extra == "dev"
Requires-Dist: flit ; extra == "dev"
Requires-Dist: sphinx ; extra == "doc"
Requires-Dist: jupyter-book ; extra == "doc"
Requires-Dist: sphinx-external-toc ; extra == "doc"
Requires-Dist: sphinx-autoapi ; extra == "doc"
Requires-Dist: sphinx-jupyterbook-latex ; extra == "doc"
Requires-Dist: pytest ; extra == "test"
Requires-Dist: werkzeug ; extra == "test"
Project-URL: Home, https://github.com/heavyai/sqlalchemy-heavyai
Project-URL: Source, https://github.com/heavyai/sqlalchemy-heavyai
Provides-Extra: dev
Provides-Extra: doc
Provides-Extra: test
